<?xml version="1.0"?>

<entity-mappings xmlns="http://java.sun.com/xml/ns/persistence/orm" xmlns:xsi="http://www.w3.org/2001/XMLSchema-instance" version="1.0" xsi:schemaLocation="http://java.sun.com/xml/ns/persistence/orm http://java.sun.com/xml/ns/persistence/orm_1_0.xsd">
	<persistence-unit-metadata>
		<xml-mapping-metadata-complete/>
		<persistence-unit-defaults>
			<access>PROPERTY</access>
		</persistence-unit-defaults>
	</persistence-unit-metadata>
	<mapped-superclass class="at.meduni.liferay.portlet.bbmrieric.model.impl.BioBankModelImpl">
		<attributes>
			<id name="biobankId" />
			<basic name="organisationid" />
			<basic name="ldapbiobankID" />
			<basic name="biobankcountry" />
			<basic name="biobankname" />
			<basic name="biobanktype" />
			<basic name="biobanksize" />
			<basic name="biobankdescription" />
			<basic name="biobankjuristicperson" />
			<basic name="UUID" />
			<transient name="modelAttributes" />
			<transient name="primaryKey" />
			<transient name="primaryKeyObj" />
		</attributes>
	</mapped-superclass>
	<mapped-superclass class="at.meduni.liferay.portlet.bbmrieric.model.impl.ContactInformationModelImpl">
		<attributes>
			<id name="contactinformationId" />
			<basic name="uuid">
				<column name="UUID_" />
			</basic>
			<basic name="companyId" />
			<basic name="groupId" />
			<basic name="userId" />
			<basic name="userName" />
			<basic name="createDate">
				<temporal>TIMESTAMP</temporal>
			</basic>
			<basic name="modifiedDate">
				<temporal>TIMESTAMP</temporal>
			</basic>
			<basic name="updateuuid" />
			<basic name="contactID" />
			<basic name="contactEmail" />
			<basic name="contactCountry" />
			<basic name="contactFirstName" />
			<basic name="contactLastName" />
			<basic name="contactPhone" />
			<basic name="contactAddress" />
			<basic name="contactZIP" />
			<basic name="contactCity" />
			<transient name="modelAttributes" />
			<transient name="primaryKey" />
			<transient name="primaryKeyObj" />
			<transient name="userUuid" />
		</attributes>
	</mapped-superclass>
	<mapped-superclass class="at.meduni.liferay.portlet.bbmrieric.model.impl.D2BiobankModelImpl">
		<attributes>
			<id name="biobankId" />
			<basic name="uuid">
				<column name="UUID_" />
			</basic>
			<basic name="status" />
			<basic name="statusByUserId" />
			<basic name="statusByUserName" />
			<basic name="statusDate">
				<temporal>TIMESTAMP</temporal>
			</basic>
			<basic name="companyId" />
			<basic name="groupId" />
			<basic name="userId" />
			<basic name="userName" />
			<basic name="createDate">
				<temporal>TIMESTAMP</temporal>
			</basic>
			<basic name="modifiedDate">
				<temporal>TIMESTAMP</temporal>
			</basic>
			<basic name="updateuuid" />
			<basic name="contactIDRef" />
			<basic name="contactPriority" />
			<basic name="bbmribiobankID" />
			<basic name="biobankName" />
			<basic name="biobankJurisdicalPerson" />
			<basic name="biobankCountry" />
			<basic name="biobankPartnerCharterSigned" />
			<basic name="bioresourceReference" />
			<basic name="biobankNetworkIDRef" />
			<basic name="geoLatitude" />
			<basic name="geoLongitude" />
			<basic name="collaborationPartnersCommercial" />
			<basic name="collaborationPartnersNonforprofit" />
			<basic name="biobankITSupportAvailable" />
			<basic name="biobankITStaffSize" />
			<basic name="biobankISAvailable" />
			<basic name="biobankHISAvailable" />
			<basic name="biobankAcronym" />
			<basic name="biobankDescription" />
			<basic name="biobankURL" />
			<basic name="biobankHeadFirstName" />
			<basic name="biobankHeadLastName" />
			<basic name="biobankHeadRole" />
			<basic name="biobankClinical" />
			<basic name="biobankPopulation" />
			<basic name="biobankResearchStudy" />
			<basic name="biobankNonHuman" />
			<basic name="biobankCollection" />
			<basic name="biobankType" />
			<transient name="modelAttributes" />
			<transient name="primaryKey" />
			<transient name="primaryKeyObj" />
			<transient name="statusByUserUuid" />
			<transient name="userUuid" />
		</attributes>
	</mapped-superclass>
	<mapped-superclass class="at.meduni.liferay.portlet.bbmrieric.model.impl.D2CollectionModelImpl">
		<attributes>
			<id name="d2collectionId" />
			<basic name="uuid">
				<column name="UUID_" />
			</basic>
			<basic name="biobankId" />
			<basic name="parentd2collectionId" />
			<basic name="companyId" />
			<basic name="groupId" />
			<basic name="userId" />
			<basic name="userName" />
			<basic name="createDate">
				<temporal>TIMESTAMP</temporal>
			</basic>
			<basic name="modifiedDate">
				<temporal>TIMESTAMP</temporal>
			</basic>
			<basic name="updateuuid" />
			<basic name="bbmricollectionID" />
			<basic name="bbmriparentcollectionID" />
			<basic name="bbmribiobankID" />
			<basic name="collectionName" />
			<basic name="materialStoredDNA" />
			<basic name="materialStoredPlasma" />
			<basic name="materialStoredSerum" />
			<basic name="materialStoredUrine" />
			<basic name="materialStoredSaliva" />
			<basic name="materialStoredFaeces" />
			<basic name="materialStoredRNA" />
			<basic name="materialStoredBlood" />
			<basic name="materialStoredTissueFrozen" />
			<basic name="materialStoredTissueFFPE" />
			<basic name="materialStoredImmortalizedCellLines" />
			<basic name="materialStoredIsolatedPathogen" />
			<basic name="materialStoredOther" />
			<basic name="collectionTypeCaseControl" />
			<basic name="collectionTypeCohort" />
			<basic name="collectionTypeCrossSectional" />
			<basic name="collectionTypeLongitudinal" />
			<basic name="collectionTypeTwinStudy" />
			<basic name="collectionTypeQualityControl" />
			<basic name="collectionTypePopulationBased" />
			<basic name="collectionTypeDiseaseSpecific" />
			<basic name="collectionTypeBirthCohort" />
			<basic name="collectionTypeOther" />
			<basic name="collectionOrderOfMagnitude" />
			<basic name="bioresourceReference" />
			<basic name="contactIDRef" />
			<basic name="contactPriority" />
			<basic name="biobankNetworkIDRef" />
			<basic name="geoLatitude" />
			<basic name="geoLongitude" />
			<basic name="collaborationPartnersCommercial" />
			<basic name="collaborationPartnersNonforprofit" />
			<basic name="collectionAcronym" />
			<basic name="collectionDescription" />
			<basic name="collectionSexMale" />
			<basic name="collectionSexFemale" />
			<basic name="collectionSexUnknown" />
			<basic name="collectionSexUndiferrentiated" />
			<basic name="collectionAgeLow" />
			<basic name="collectionAgeHigh" />
			<basic name="collectionAgeUnit" />
			<basic name="collectionAvailableBiologicalSamples" />
			<basic name="collectionAvailableSurveyData" />
			<basic name="collectionAvailableImagingData" />
			<basic name="collectionAvailableMedicalRecords" />
			<basic name="collectionAvailableNationalRegistries" />
			<basic name="collectionAvailableGenealogicalRecords" />
			<basic name="collectionAvailablePhysioBiochemMeasurements" />
			<basic name="collectionAvailableOther" />
			<basic name="temperatureRoom" />
			<basic name="temperature2to10" />
			<basic name="temperature18to35" />
			<basic name="temperature60to85" />
			<basic name="temperatureLN" />
			<basic name="temperatureOther" />
			<basic name="diagnosisAvailable" />
			<basic name="collectionHeadFirstName" />
			<basic name="collectionHeadLastName" />
			<basic name="collectionHeadRole" />
			<basic name="collectionSampleAccessFee" />
			<basic name="collectionSampleAccessJointProjects" />
			<basic name="collectionSampleAccessDescription" />
			<basic name="collectionSampleAccessURI" />
			<basic name="collectionDataAccessFee" />
			<basic name="collectionDataAccessJointProjects" />
			<basic name="collectionDataAccessDescription" />
			<basic name="collectionDataAccessURI" />
			<basic name="collectionSize" />
			<basic name="collectionSizeTimestamp" />
			<transient name="modelAttributes" />
			<transient name="primaryKey" />
			<transient name="primaryKeyObj" />
			<transient name="userUuid" />
		</attributes>
	</mapped-superclass>
	<mapped-superclass class="at.meduni.liferay.portlet.bbmrieric.model.impl.DiseaseDiscriptionModelImpl">
		<attributes>
			<id name="diseasediscriptionId" />
			<basic name="diseasecode" />
			<basic name="diseasegroup" />
			<basic name="diseasediscription" />
			<basic name="root" />
			<transient name="modelAttributes" />
			<transient name="primaryKey" />
			<transient name="primaryKeyObj" />
		</attributes>
	</mapped-superclass>
	<mapped-superclass class="at.meduni.liferay.portlet.bbmrieric.model.impl.SearchIndexModelImpl">
		<attributes>
			<id name="searchid" />
			<basic name="organisationid" />
			<basic name="locationid" />
			<basic name="location" />
			<basic name="searchindexkey" />
			<basic name="searchindexvalue" />
			<basic name="UUID" />
			<transient name="modelAttributes" />
			<transient name="primaryKey" />
			<transient name="primaryKeyObj" />
		</attributes>
	</mapped-superclass>
	<entity class="at.meduni.liferay.portlet.bbmrieric.model.impl.BioBankImpl" name="BioBank">
		<table name="bbmrieric.biobank" />
		<attributes />
	</entity>
	<entity class="at.meduni.liferay.portlet.bbmrieric.model.impl.ContactInformationImpl" name="ContactInformation">
		<table name="bbmrieric.contactinformation" />
		<attributes />
	</entity>
	<entity class="at.meduni.liferay.portlet.bbmrieric.model.impl.D2BiobankImpl" name="D2Biobank">
		<table name="bbmrieric.d2biobank" />
		<attributes />
	</entity>
	<entity class="at.meduni.liferay.portlet.bbmrieric.model.impl.D2CollectionImpl" name="D2Collection">
		<table name="bbmrieric.d2collection" />
		<attributes />
	</entity>
	<entity class="at.meduni.liferay.portlet.bbmrieric.model.impl.DiseaseDiscriptionImpl" name="DiseaseDiscription">
		<table name="bbmrieric.diseasediscription" />
		<attributes />
	</entity>
	<entity class="at.meduni.liferay.portlet.bbmrieric.model.impl.SearchIndexImpl" name="SearchIndex">
		<table name="bbmrieric.searchindex" />
		<attributes />
	</entity>
</entity-mappings>