<?xml version="1.0"?>

<model-hints>
	<model name="at.graz.meduni.liferay.portlet.bibbox.service.model.BiobankPanelAssessment">
		<field name="biobankpanelassessmentId" type="long" />
		<field name="organizationId" type="long" />
		<field name="userId" type="long" />
		<field name="dateofassessment" type="Date" />
		<field name="background1_1" type="String" />
		<field name="background1_1_comments" type="String">
			<hint name="max-length">5000</hint>
		</field>
		<field name="elsi1_2" type="String" />
		<field name="quality1_3" type="String" />
		<field name="quality1_3_comments" type="String">
			<hint name="max-length">5000</hint>
		</field>
		<field name="cataloguemeetpurposes2_1" type="String" />
		<field name="adequateitplatform2_2" type="String" />
		<field name="addedvaluecatalogue2_3" type="String" />
		<field name="associateddata2_4" type="String" />
		<field name="associateddata2_4_comments" type="String">
			<hint name="max-length">5000</hint>
		</field>
		<field name="reasonstoaccept3_1" type="String">
			<hint name="max-length">5000</hint>
		</field>
		<field name="recommendation3_2" type="String">
			<hint name="max-length">5000</hint>
		</field>
		<field name="needadditionalinformation3_3" type="String">
			<hint name="max-length">5000</hint>
		</field>
		<field name="finalrecommendation_4" type="String">
			<hint name="max-length">5000</hint>
		</field>
	</model>
	<model name="at.graz.meduni.liferay.portlet.bibbox.service.model.Invitation">
		<field name="invitationId" type="long" />
		<field name="name" type="String" />
		<field name="subject" type="String">
			<hint name="max-length">255</hint>
		</field>
		<field name="body" type="String">
			<hint name="max-length">5000</hint>
		</field>
		<field name="status" type="long" />
		<field name="invitationsend" type="Date" />
		<field name="lastchanged" type="Date" />
		<field name="lastchanger" type="long" />
		<field name="filter" type="String" />
	</model>
	<model name="at.graz.meduni.liferay.portlet.bibbox.service.model.InvitationOrganisation">
		<field name="invitationOrganisationId" type="long" />
		<field name="invitationId" type="long" />
		<field name="organisationId" type="long" />
		<field name="userId" type="long" />
		<field name="lastchanged" type="Date" />
		<field name="lastchanger" type="long" />
		<field name="reactdate" type="Date" />
		<field name="lastusedlink" type="Date" />
		<field name="rejectdate" type="Date" />
		<field name="securitylinktoken" type="long" />
		<field name="securitytoken" type="long" />
		<field name="status" type="long" />
		<field name="statusdate" type="Date" />
	</model>
</model-hints>